app/__init__.py
app/core/__init__.py
app/core/config.py
dbinpect-0.1.2.dist-info/licenses/LICENSE
scripts/db_inspector.py
dbinpect-0.1.2.dist-info/METADATA
dbinpect-0.1.2.dist-info/WHEEL
dbinpect-0.1.2.dist-info/entry_points.txt
dbinpect-0.1.2.dist-info/top_level.txt
dbinpect-0.1.2.dist-info/RECORD
