Metadata-Version: 2.4
Name: dbinpect
Version: 0.1.2
Summary: Outil d'inspection et d'analyse de bases de données
Author-email: Herolde GUIELLE <ashguiell@gmail.com>
License: MIT
Project-URL: Homepage, https://github.com/AshBrud/dbinpect
Project-URL: Documentation, https://github.com/AshBrud/dbinpect#readme
Project-URL: Repository, https://github.com/AshBrud/dbinpect
Project-URL: Issues, https://github.com/AshBrud/dbinpect/issues
Keywords: database,inspection,sqlalchemy,analysis
Classifier: Development Status :: 3 - Alpha
Classifier: Intended Audience :: Developers
Classifier: License :: OSI Approved :: MIT License
Classifier: Programming Language :: Python :: 3
Classifier: Programming Language :: Python :: 3.8
Classifier: Programming Language :: Python :: 3.9
Classifier: Programming Language :: Python :: 3.10
Classifier: Programming Language :: Python :: 3.11
Classifier: Topic :: Database
Requires-Python: >=3.8
License-File: LICENSE
Requires-Dist: SQLAlchemy>=2.0
Requires-Dist: pydantic>=2.0
Requires-Dist: pydantic-settings>=2.0
Requires-Dist: python-dotenv>=1.0
Dynamic: license-file
